dc_chat_exporter/__init__.py
dc_chat_exporter/exporter.py
dc_chat_exporter/template.html
dc_chat_exporter-0.1.0.dist-info/METADATA
dc_chat_exporter-0.1.0.dist-info/WHEEL
dc_chat_exporter-0.1.0.dist-info/top_level.txt
dc_chat_exporter-0.1.0.dist-info/RECORD
