Metadata-Version: 2.4
Name: dc-chat-exporter
Version: 0.1.0
Summary: Export Discord chats to beautiful HTML files
Author: miguel_meier
License: MIT
Project-URL: GitHub, https://github.com/miguelmeier/discord-chat-exporter-python
Keywords: discord,bot,chat-exporter,chat
Classifier: Development Status :: 4 - Beta
Classifier: License :: OSI Approved :: MIT License
Classifier: Intended Audience :: Developers
Classifier: Operating System :: OS Independent
Classifier: Programming Language :: Python :: 3.9
Classifier: Programming Language :: Python :: 3.10
Classifier: Programming Language :: Python :: 3.11
Classifier: Programming Language :: Python :: 3.12
Classifier: Programming Language :: Python :: 3.13
Requires-Python: >=3.9
Requires-Dist: discord.py>=2.0.0
Requires-Dist: aiohttp>=3.8.0
